voxcell/__init__.py
voxcell/cell_collection.py
voxcell/exceptions.py
voxcell/math_utils.py
voxcell/quaternion.py
voxcell/region_map.py
voxcell/traits.py
voxcell/vector_fields.py
voxcell/voxel_data.py
voxcell/nexus/__init__.py
voxcell/nexus/voxelbrain.py
voxcell/sonata/__init__.py
voxcell/sonata/node_population.py
voxcell/utils/__init__.py
voxcell/utils/deprecate.py
voxcell-3.1.10.dist-info/licenses/AUTHORS.txt
voxcell-3.1.10.dist-info/licenses/LICENSE.txt
voxcell-3.1.10.dist-info/METADATA
voxcell-3.1.10.dist-info/WHEEL
voxcell-3.1.10.dist-info/top_level.txt
voxcell-3.1.10.dist-info/RECORD
