Metadata-Version: 2.4
Name: voxcell
Version: 3.1.10
Summary: Voxcell is a small library to handle probability distributions that have a spatial component and to use them to build collection of cells in space.
Home-page: https://github.com/BlueBrain/voxcell
Download-URL: https://github.com/BlueBrain/voxcell
Author: Blue Brain Project, EPFL
License: Apache-2
Classifier: Development Status :: 2 - Pre-Alpha
Classifier: Programming Language :: Python
Classifier: Programming Language :: Python :: 3
Classifier: Programming Language :: Python :: 3.8
Classifier: Programming Language :: Python :: 3.9
Classifier: Programming Language :: Python :: 3.10
Classifier: Programming Language :: Python :: 3.11
Classifier: Programming Language :: Python :: 3.12
Requires-Python: >=3.8
License-File: LICENSE.txt
License-File: AUTHORS.txt
Requires-Dist: h5py>=3.1.0
Requires-Dist: numpy>=1.9
Requires-Dist: pandas>=0.24.2
Requires-Dist: pynrrd>=1.1.0
Requires-Dist: requests>=2.18
Requires-Dist: scipy>=1.2.0
Provides-Extra: docs
Requires-Dist: sphinx-bluebrain-theme; extra == "docs"
Dynamic: author
Dynamic: classifier
Dynamic: description
Dynamic: description-content-type
Dynamic: download-url
Dynamic: home-page
Dynamic: license
Dynamic: license-file
Dynamic: provides-extra
Dynamic: requires-dist
Dynamic: requires-python
Dynamic: summary
